{"sections":{"section_fPjfim":{"type":"section","blocks":{"text_6dr69z":{"type":"text","settings":{"text":"<p>Contact<\/p>","width":"100%","max_width":"normal","alignment":"center","type_preset":"h2","font":"var(--font-primary--family)","font_size":"","line_height":"normal","letter_spacing":"normal","case":"none","wrap":"pretty","color":"","background":false,"background_color":"#00000026","corner_radius":0,"padding-block-start":100,"padding-block-end":0,"padding-inline-start":40,"padding-inline-end":0},"blocks":{}}},"block_order":["text_6dr69z"],"settings":{"content_direction":"row","vertical_on_mobile":true,"horizontal_alignment":"flex-start","vertical_alignment":"center","align_baseline":false,"horizontal_alignment_flex_direction_column":"flex-start","vertical_alignment_flex_direction_column":"center","gap":12,"section_width":"full-width","section_height":"","section_height_custom":50,"color_scheme":"scheme-5","background_media":"image","video_position":"cover","background_image":"shopify:\/\/shop_images\/synapex-herp-img-clean.png","background_image_position":"cover","border":"none","border_width":1,"border_opacity":100,"border_radius":0,"toggle_overlay":true,"overlay_color":"#2563eb1a","overlay_style":"solid","gradient_direction":"to top","padding-block-start":100,"padding-block-end":32}},"section":{"type":"section","blocks":{"contact_form_jWxXkm":{"type":"contact-form","settings":{"width":"custom","custom_width":100,"width_mobile":"custom","custom_width_mobile":100,"inherit_color_scheme":true,"color_scheme":"scheme-1","padding-block-start":0,"padding-block-end":0,"padding-inline-start":0,"padding-inline-end":0},"blocks":{"submit-button":{"type":"contact-form-submit-button","static":true,"settings":{"label":"Send","style_class":"button","width":"fit-content","custom_width":100,"width_mobile":"fit-content","custom_width_mobile":100},"blocks":{}}},"block_order":[]}},"block_order":["contact_form_jWxXkm"],"settings":{"content_direction":"column","vertical_on_mobile":true,"horizontal_alignment":"flex-start","vertical_alignment":"center","align_baseline":false,"horizontal_alignment_flex_direction_column":"flex-start","vertical_alignment_flex_direction_column":"center","gap":30,"section_width":"page-width","section_height":"","section_height_custom":50,"color_scheme":"scheme-5","background_media":"none","video_position":"cover","background_image_position":"cover","border":"none","border_width":1,"border_opacity":100,"border_radius":0,"toggle_overlay":false,"overlay_color":"#00000026","overlay_style":"solid","gradient_direction":"to top","padding-block-start":40,"padding-block-end":70}},"section_WT8kUB":{"type":"section","blocks":{"group_zP9iQz":{"type":"group","settings":{"link":"","open_in_new_tab":false,"content_direction":"column","vertical_on_mobile":true,"horizontal_alignment":"flex-start","vertical_alignment":"center","align_baseline":false,"horizontal_alignment_flex_direction_column":"center","vertical_alignment_flex_direction_column":"center","gap":16,"width":"fill","custom_width":100,"width_mobile":"fill","custom_width_mobile":100,"height":"fit","custom_height":100,"inherit_color_scheme":true,"color_scheme":"","background_media":"none","video_position":"cover","background_image_position":"cover","border":"none","border_width":1,"border_opacity":100,"border_radius":0,"toggle_overlay":false,"overlay_color":"#00000026","overlay_style":"solid","gradient_direction":"to top","padding-block-start":0,"padding-block-end":0,"padding-inline-start":0,"padding-inline-end":0},"blocks":{"icon_GLCmFX":{"type":"icon","settings":{"icon":"chat_bubble","width":32,"link":"","open_in_new_tab":false},"blocks":{}},"group_XhbnEb":{"type":"group","settings":{"link":"","open_in_new_tab":false,"content_direction":"column","vertical_on_mobile":true,"horizontal_alignment":"flex-start","vertical_alignment":"center","align_baseline":false,"horizontal_alignment_flex_direction_column":"flex-start","vertical_alignment_flex_direction_column":"center","gap":4,"width":"fill","custom_width":100,"width_mobile":"fill","custom_width_mobile":100,"height":"fit","custom_height":100,"inherit_color_scheme":true,"color_scheme":"","background_media":"none","video_position":"cover","background_image_position":"cover","border":"none","border_width":1,"border_opacity":100,"border_radius":0,"toggle_overlay":false,"overlay_color":"#00000026","overlay_style":"solid","gradient_direction":"to top","padding-block-start":0,"padding-block-end":0,"padding-inline-start":0,"padding-inline-end":0},"blocks":{"text_HCmkDe":{"type":"text","settings":{"text":"<h2>Email<\/h2>","width":"100%","max_width":"normal","alignment":"center","type_preset":"h3","font":"var(--font-body--family)","font_size":"","line_height":"normal","letter_spacing":"normal","case":"none","wrap":"pretty","color":"var(--color-foreground)","background":false,"background_color":"#00000026","corner_radius":0,"padding-block-start":0,"padding-block-end":0,"padding-inline-start":0,"padding-inline-end":0},"blocks":{}},"text_wc4WAc":{"type":"text","settings":{"text":"<p>Everything we do starts with why<\/p>","width":"100%","max_width":"normal","alignment":"center","type_preset":"rte","font":"var(--font-body--family)","font_size":"","line_height":"normal","letter_spacing":"normal","case":"none","wrap":"pretty","color":"var(--color-foreground)","background":false,"background_color":"#00000026","corner_radius":0,"padding-block-start":0,"padding-block-end":0,"padding-inline-start":0,"padding-inline-end":0},"blocks":{}}},"block_order":["text_HCmkDe","text_wc4WAc"]}},"block_order":["icon_GLCmFX","group_XhbnEb"]},"group_7zhg8q":{"type":"group","settings":{"link":"","open_in_new_tab":false,"content_direction":"column","vertical_on_mobile":true,"horizontal_alignment":"flex-start","vertical_alignment":"center","align_baseline":false,"horizontal_alignment_flex_direction_column":"center","vertical_alignment_flex_direction_column":"center","gap":16,"width":"fill","custom_width":100,"width_mobile":"fill","custom_width_mobile":100,"height":"fit","custom_height":100,"inherit_color_scheme":true,"color_scheme":"","background_media":"none","video_position":"cover","background_image_position":"cover","border":"none","border_width":1,"border_opacity":100,"border_radius":0,"toggle_overlay":false,"overlay_color":"#00000026","overlay_style":"solid","gradient_direction":"to top","padding-block-start":0,"padding-block-end":0,"padding-inline-start":0,"padding-inline-end":0},"blocks":{"icon_W6QeMt":{"type":"icon","settings":{"icon":"whatsapp","width":32,"link":"","open_in_new_tab":false},"blocks":{}},"group_qdpxdX":{"type":"group","settings":{"link":"","open_in_new_tab":false,"content_direction":"column","vertical_on_mobile":true,"horizontal_alignment":"flex-start","vertical_alignment":"center","align_baseline":false,"horizontal_alignment_flex_direction_column":"flex-start","vertical_alignment_flex_direction_column":"center","gap":4,"width":"fill","custom_width":100,"width_mobile":"fill","custom_width_mobile":100,"height":"fit","custom_height":100,"inherit_color_scheme":true,"color_scheme":"","background_media":"none","video_position":"cover","background_image_position":"cover","border":"none","border_width":1,"border_opacity":100,"border_radius":0,"toggle_overlay":false,"overlay_color":"#00000026","overlay_style":"solid","gradient_direction":"to top","padding-block-start":0,"padding-block-end":0,"padding-inline-start":0,"padding-inline-end":0},"blocks":{"text_nUzdRi":{"type":"text","settings":{"text":"<h2>Phone<\/h2>","width":"100%","max_width":"normal","alignment":"center","type_preset":"h3","font":"var(--font-body--family)","font_size":"","line_height":"normal","letter_spacing":"normal","case":"none","wrap":"pretty","color":"var(--color-foreground)","background":false,"background_color":"#00000026","corner_radius":0,"padding-block-start":0,"padding-block-end":0,"padding-inline-start":0,"padding-inline-end":0},"blocks":{}},"text_Fq3tE8":{"type":"text","settings":{"text":"<p>We believe in building better<\/p>","width":"100%","max_width":"normal","alignment":"center","type_preset":"rte","font":"var(--font-body--family)","font_size":"","line_height":"normal","letter_spacing":"normal","case":"none","wrap":"pretty","color":"var(--color-foreground)","background":false,"background_color":"#00000026","corner_radius":0,"padding-block-start":0,"padding-block-end":0,"padding-inline-start":0,"padding-inline-end":0},"blocks":{}}},"block_order":["text_nUzdRi","text_Fq3tE8"]}},"block_order":["icon_W6QeMt","group_qdpxdX"]},"group_dewLxP":{"type":"group","settings":{"link":"","open_in_new_tab":false,"content_direction":"column","vertical_on_mobile":true,"horizontal_alignment":"flex-start","vertical_alignment":"center","align_baseline":false,"horizontal_alignment_flex_direction_column":"center","vertical_alignment_flex_direction_column":"center","gap":16,"width":"fill","custom_width":100,"width_mobile":"fill","custom_width_mobile":100,"height":"fit","custom_height":100,"inherit_color_scheme":true,"color_scheme":"","background_media":"none","video_position":"cover","background_image_position":"cover","border":"none","border_width":1,"border_opacity":100,"border_radius":0,"toggle_overlay":false,"overlay_color":"#00000026","overlay_style":"solid","gradient_direction":"to top","padding-block-start":0,"padding-block-end":0,"padding-inline-start":0,"padding-inline-end":0},"blocks":{"icon_WJARiC":{"type":"icon","settings":{"icon":"lightning_bolt","width":32,"link":"","open_in_new_tab":false},"blocks":{}},"group_DjmTPy":{"type":"group","settings":{"link":"","open_in_new_tab":false,"content_direction":"column","vertical_on_mobile":true,"horizontal_alignment":"flex-start","vertical_alignment":"center","align_baseline":false,"horizontal_alignment_flex_direction_column":"flex-start","vertical_alignment_flex_direction_column":"center","gap":4,"width":"fill","custom_width":100,"width_mobile":"fill","custom_width_mobile":100,"height":"fit","custom_height":100,"inherit_color_scheme":true,"color_scheme":"","background_media":"none","video_position":"cover","background_image_position":"cover","border":"none","border_width":1,"border_opacity":100,"border_radius":0,"toggle_overlay":false,"overlay_color":"#00000026","overlay_style":"solid","gradient_direction":"to top","padding-block-start":0,"padding-block-end":0,"padding-inline-start":0,"padding-inline-end":0},"blocks":{"text_F7Y6H4":{"type":"text","settings":{"text":"<h2>Order Issue<\/h2>","width":"100%","max_width":"normal","alignment":"center","type_preset":"h3","font":"var(--font-body--family)","font_size":"","line_height":"normal","letter_spacing":"normal","case":"none","wrap":"pretty","color":"var(--color-foreground)","background":false,"background_color":"#00000026","corner_radius":0,"padding-block-start":0,"padding-block-end":0,"padding-inline-start":0,"padding-inline-end":0},"blocks":{}},"text_6UmGBY":{"type":"text","settings":{"text":"<p>Real people making great products<\/p>","width":"100%","max_width":"normal","alignment":"center","type_preset":"rte","font":"var(--font-body--family)","font_size":"","line_height":"normal","letter_spacing":"normal","case":"none","wrap":"pretty","color":"var(--color-foreground)","background":false,"background_color":"#00000026","corner_radius":0,"padding-block-start":0,"padding-block-end":0,"padding-inline-start":0,"padding-inline-end":0},"blocks":{}}},"block_order":["text_F7Y6H4","text_6UmGBY"]}},"block_order":["icon_WJARiC","group_DjmTPy"]}},"block_order":["group_zP9iQz","group_7zhg8q","group_dewLxP"],"settings":{"content_direction":"row","vertical_on_mobile":true,"horizontal_alignment":"flex-start","vertical_alignment":"center","align_baseline":false,"horizontal_alignment_flex_direction_column":"flex-start","vertical_alignment_flex_direction_column":"center","gap":16,"section_width":"page-width","section_height":"","section_height_custom":50,"color_scheme":"scheme-5","background_media":"none","video_position":"cover","background_image_position":"cover","border":"none","border_width":1,"border_opacity":100,"border_radius":0,"toggle_overlay":false,"overlay_color":"#00000026","overlay_style":"solid","gradient_direction":"to top","padding-block-start":48,"padding-block-end":48}}},"order":["section_fPjfim","section","section_WT8kUB"]}